pyqt_image_file_explorer_table_widget/__init__.py
pyqt_image_file_explorer_table_widget/imageFileExplorerTableWidget.py
pyqt_image_file_explorer_table_widget/imageLabelWidget.py
pyqt_image_file_explorer_table_widget/imageWidget.py
pyqt_image_file_explorer_table_widget/style/__init__.py
pyqt_image_file_explorer_table_widget/style/image.css
pyqt_image_file_explorer_table_widget/style/table.css
pyqt_image_file_explorer_table_widget-0.0.1.dist-info/LICENSE
pyqt_image_file_explorer_table_widget-0.0.1.dist-info/METADATA
pyqt_image_file_explorer_table_widget-0.0.1.dist-info/WHEEL
pyqt_image_file_explorer_table_widget-0.0.1.dist-info/top_level.txt
pyqt_image_file_explorer_table_widget-0.0.1.dist-info/RECORD
