Metadata-Version: 2.1
Name: pyqt-image-file-explorer-table-widget
Version: 0.0.1
Summary: PyQt QTableWidget for image file explorer
Home-page: https://github.com/yjg30737/pyqt-image-file-explorer-table-widget.git
Author: Jung Gyu Yoon
Author-email: yjg30737@gmail.com
License: MIT
Platform: UNKNOWN
License-File: LICENSE
Requires-Dist: PyQt5 (>=5.8)
Requires-Dist: pyqt-resource-helper (>=0.0.1)
